{
  "entities": {
    "Revenue": {
      "$schema": "http://json-schema.org/draft-07/schema#",
      "title": "Revenue",
      "type": "object",
      "description": "Represents a revenue transaction.",
      "properties": {
        "id": {
          "type": "string",
          "description": "Unique identifier for the revenue transaction."
        },
        "source": {
          "type": "string",
          "description": "The source of the revenue (e.g., customer name, service provided)."
        },
        "date": {
          "type": "string",
          "description": "The date of the revenue transaction.",
          "format": "date-time"
        },
        "amount": {
          "type": "number",
          "description": "The amount of the revenue transaction."
        },
        "category": {
          "type": "string",
          "description": "The category of the revenue (e.g., sales, services)."
        }
      },
      "required": [
        "id",
        "source",
        "date",
        "amount",
        "category"
      ]
    },
    "Expense": {
      "$schema": "http://json-schema.org/draft-07/schema#",
      "title": "Expense",
      "type": "object",
      "description": "Represents an expense transaction.",
      "properties": {
        "id": {
          "type": "string",
          "description": "Unique identifier for the expense transaction."
        },
        "vendor": {
          "type": "string",
          "description": "The vendor or supplier for the expense."
        },
        "date": {
          "type": "string",
          "description": "The date of the expense transaction.",
          "format": "date-time"
        },
        "amount": {
          "type": "number",
          "description": "The amount of the expense transaction."
        },
        "category": {
          "type": "string",
          "description": "The category of the expense (e.g., rent, utilities)."
        }
      },
      "required": [
        "id",
        "vendor",
        "date",
        "amount",
        "category"
      ]
    },
    "Appointment": {
      "$schema": "http://json-schema.org/draft-07/schema#",
      "title": "Appointment",
      "type": "object",
      "description": "Represents a scheduled appointment.",
      "properties": {
        "id": {
          "type": "string",
          "description": "Unique identifier for the appointment."
        },
        "title": {
          "type": "string",
          "description": "The title or subject of the appointment."
        },
        "startTime": {
          "type": "string",
          "description": "The start date and time of the appointment.",
          "format": "date-time"
        },
        "endTime": {
          "type": "string",
          "description": "The end date and time of the appointment.",
          "format": "date-time"
        },
        "description": {
          "type": "string",
          "description": "A description or notes about the appointment."
        }
      },
      "required": [
        "id",
        "title",
        "startTime",
        "endTime"
      ]
    }
  },
  "auth": {
    "providers": [
      "password",
      "anonymous"
    ]
  },
  "firestore": {
    "structure": [
      {
        "path": "/users/{userId}/revenues/{revenueId}",
        "definition": {
          "entityName": "Revenue",
          "schema": {
            "$ref": "#/backend/entities/Revenue"
          },
          "description": "Stores revenue transactions for a specific user. Uses path-based ownership for security. All revenues under a user id is owned by the user.",
          "params": [
            {
              "name": "userId",
              "description": "The unique identifier of the user."
            },
            {
              "name": "revenueId",
              "description": "The unique identifier of the revenue transaction."
            }
          ]
        }
      },
      {
        "path": "/users/{userId}/expenses/{expenseId}",
        "definition": {
          "entityName": "Expense",
          "schema": {
            "$ref": "#/backend/entities/Expense"
          },
          "description": "Stores expense transactions for a specific user. Uses path-based ownership for security. All expenses under a user id is owned by the user.",
          "params": [
            {
              "name": "userId",
              "description": "The unique identifier of the user."
            },
            {
              "name": "expenseId",
              "description": "The unique identifier of the expense transaction."
            }
          ]
        }
      },
      {
        "path": "/users/{userId}/appointments/{appointmentId}",
        "definition": {
          "entityName": "Appointment",
          "schema": {
            "$ref": "#/backend/entities/Appointment"
          },
          "description": "Stores appointments for a specific user. Uses path-based ownership for security. All appointments under a user id is owned by the user.",
          "params": [
            {
              "name": "userId",
              "description": "The unique identifier of the user."
            },
            {
              "name": "appointmentId",
              "description": "The unique identifier of the appointment."
            }
          ]
        }
      }
    ],
    "reasoning": "The Firestore data structure is designed to provide a secure and scalable solution for the BizSight application, focusing on authorization independence and clear data segregation. The structure leverages path-based ownership for user-specific data, enabling straightforward security rules and efficient data retrieval. Each user's data (revenues, expenses, and appointments) are stored under their respective user ID, ensuring data isolation and simplified access control. Revenue and expense are kept under the `user/{userid}` root, and appointments are stored under `appointments/{userid}`. This segregation enables secure list operations (QAPs) as rules only need to validate `request.auth.uid` against the wildcard `{userId}`. This design eliminates the need for complex `get()` calls in security rules, fostering authorization independence and simplifying debugging. The absence of a collaborative requirement removes the necessity for membership maps, further simplifying the structure and enhancing security."
  }
}